distribute_config/__init__.py
distribute_config/variable.py
distribute_config/tests/__init__.py
distribute_config-0.0.1.dist-info/LICENSE
distribute_config-0.0.1.dist-info/METADATA
distribute_config-0.0.1.dist-info/WHEEL
distribute_config-0.0.1.dist-info/top_level.txt
distribute_config-0.0.1.dist-info/RECORD
