Metadata-Version: 2.1
Name: distribute-config
Version: 0.0.1
Summary: A package to handle multi-source distributed configuration
Home-page: https://github.com/Net-Mist/distribute_config
Author: Sébastien IOOSS
Author-email: archimist.linux@gmail.com
License: UNKNOWN
Platform: UNKNOWN
Classifier: Programming Language :: Python :: 3
Classifier: License :: OSI Approved :: MIT License
Classifier: Operating System :: OS Independent
